Metadata-Version: 2.1
Name: payslip-br
Version: 0.0.2
Summary: A Python module for decoding and working with Brazilian payslips, more commonly known as boletos.
Home-page: https://github.com/gambardellawill/payslip
Author: William Gambardella
Author-email: williamcampo@gmail.com
License: UNKNOWN
Project-URL: Bug tracker, https://github.com/gambardellawill/payslip/issues
Platform: UNKNOWN
Classifier: Programming Language :: Python :: 3
Classifier: Development Status :: 2 - Pre-Alpha
Classifier: Operating System :: OS Independent
Classifier: Intended Audience :: Developers
Classifier: Topic :: Office/Business :: Financial
Requires-Python: >=3.5
License-File: LICENSE
